async_redis_uow/__init__.py
async_redis_uow/repository/__init__.py
async_redis_uow/repository/adder.py
async_redis_uow/repository/all_getter.py
async_redis_uow/repository/base.py
async_redis_uow/repository/base_setter.py
async_redis_uow/repository/common.py
async_redis_uow/repository/deleter.py
async_redis_uow/repository/getter.py
async_redis_uow/repository/paginated.py
async_redis_uow/repository/paginated_all_getter.py
async_redis_uow/repository/status_updater.py
async_redis_uow/repository/types.py
async_redis_uow/repository/updateter.py
async_redis_uow/session_maker/__init__.py
async_redis_uow/session_maker/session.py
async_redis_uow/session_maker/session_maker.py
async_redis_uow/utils/__init__.py
async_redis_uow/utils/creation.py
async_redis_uow-0.0.20.dist-info/METADATA
async_redis_uow-0.0.20.dist-info/WHEEL
async_redis_uow-0.0.20.dist-info/top_level.txt
async_redis_uow-0.0.20.dist-info/RECORD
