Metadata-Version: 2.1
Name: async_redis_uow
Version: 0.0.20
Summary: Implementation of async axabc.uow pattern using pyredis
Author: axdjuraev
Author-email: <axdjuraev@gmail.com>
Requires-Dist: axabc
Requires-Dist: redis
